znflow/__init__.py
znflow/base.py
znflow/combine.py
znflow/dynamic.py
znflow/exceptions.py
znflow/graph.py
znflow/handler.py
znflow/node.py
znflow/utils.py
znflow/visualize.py
znflow/deployment/__init__.py
znflow/deployment/base.py
znflow/deployment/dask_depl.py
znflow/deployment/vanilla.py
znflow-0.2.7.dist-info/METADATA
znflow-0.2.7.dist-info/WHEEL
znflow-0.2.7.dist-info/licenses/LICENSE
znflow-0.2.7.dist-info/RECORD
