Metadata-Version: 2.4
Name: znflow
Version: 0.2.7
Summary: A general purpose framework for building and running computational graphs.
Project-URL: Repository, https://github.com/zincware/znflow
Project-URL: Releases, https://github.com/zincware/znflow/releases
Project-URL: Discord, https://discord.gg/7ncfwhsnm4
Author-email: Fabian Zills <fzills@icp.uni-stuttgart.de>
License-Expression: Apache-2.0
License-File: LICENSE
Requires-Python: >=3.10
Requires-Dist: networkx>=3.4.2
